bmkg/__init__.py
bmkg/api/__init__.py
bmkg/api/api.py
bmkg/api/earthquake.py
bmkg/api/shakemap.py
bmkg/api/weather_forecast.py
bmkg/enums/__init__.py
bmkg/enums/cardinal.py
bmkg/enums/weather.py
bmkg/exceptions.py
bmkg/parsers/__init__.py
bmkg/parsers/parse_earthquake_data.py
bmkg/parsers/parse_felt_earthquake_data.py
bmkg/parsers/parse_latest_earthquake_data.py
bmkg/parsers/parse_location_data.py
bmkg/parsers/parse_strong_earthquake_data.py
bmkg/parsers/parse_weather_data.py
bmkg/parsers/parse_weather_forecast_data.py
bmkg/py.typed
bmkg/schemas/__init__.py
bmkg/schemas/coordinate.py
bmkg/schemas/earthquake.py
bmkg/schemas/felt_earthquake.py
bmkg/schemas/latest_earthquake.py
bmkg/schemas/location.py
bmkg/schemas/shakemap.py
bmkg/schemas/strong_earthquake.py
bmkg/schemas/weather.py
bmkg/schemas/weather_forecast.py
bmkg/types.py
pybmkg-3.0.1.dist-info/LICENSE
pybmkg-3.0.1.dist-info/METADATA
pybmkg-3.0.1.dist-info/WHEEL
pybmkg-3.0.1.dist-info/RECORD
