Metadata-Version: 2.1
Name: PyBMKG
Version: 3.0.1
Summary: Python BMKG API Wrapper
Home-page: https://github.com/kiraware/PyBMKG
License: MIT
Keywords: bmkg,api
Author: Kira
Author-email: kiraware@github.com
Maintainer: Kira
Maintainer-email: kiraware@github.com
Requires-Python: >=3.11,<4.0
Classifier: Development Status :: 5 - Production/Stable
Classifier: Environment :: Web Environment
Classifier: Framework :: AsyncIO
Classifier: Framework :: aiohttp
Classifier: Intended Audience :: Developers
Classifier: License :: OSI Approved :: MIT License
Classifier: Operating System :: OS Independent
Classifier: Programming Language :: Python :: 3
Classifier: Programming Language :: Python :: 3.11
Classifier: Programming Language :: Python :: 3.12
Classifier: Programming Language :: Python :: 3.13
Classifier: Topic :: Scientific/Engineering :: Atmospheric Science
Classifier: Topic :: Software Development
Requires-Dist: aiohttp (>=3.9.1,<4.0.0)
Project-URL: Bug Tracker, https://github.com/kiraware/PyBMKG/issues
Project-URL: Documentation, https://pybmkg.readthedocs.io/en/latest/
Project-URL: Repository, https://github.com/kiraware/PyBMKG
